Workbook

Sheet Start here
B2: Aurelius code map
B3: Every file in the project: what it does, how it connects, and how to explain it.
B5: Your progress
B6: Files in the map | C6: =COUNTA(Files!$D$2:$D$424) -> 423
B7: Must-read files (priority 1) | C7: =COUNTIF(Files!$F$2:$F$424,1) -> 117
B8: Files you've marked as read | C8: =COUNTIF(Files!$K$2:$K$424,"Yes") -> 0
B9: Must-read files you've read | C9: =COUNTIFS(Files!$F$2:$F$424,1,Files!$K$2:$K$424,"Yes") -> 0
B10: Must-read progress | C10: =IF(C7=0,0,C9/C7) -> 0
B12: How to use this workbook
B13: Start here | C13: This page: progress and a suggested reading order.
B14: Components | C14: One row per agent or app: language, port, what it does, its skills, who it talks to, and how many files it has.
B15: Files | C15: One row per file. Filter by Component, Category or Priority. Mark the yellow column Yes as you finish a file; the progress above updates.
B16: Request flows | C16: Five real requests followed file by file across languages. The fastest way to see how it fits together.
B17: Concepts | C17: The ideas that repeat across the system (contract, tokens, trace IDs, MCP, RAG, SSE...) and where each lives.
B18: Priority | C18: 1 = must read (entry points, core logic, contracts), 2 = useful, 3 = boilerplate, data or docs.
B20: Suggested reading order
B21: 1. The shape | C21: Components sheet top to bottom, then Request flow 2 (open a household). You'll see every agent once.
B22: 2. One agent end to end | C22: Filter Files to Liaison, priority 1: server.ts -> app.ts -> contract.ts -> skills -> store. Then run its tests.
B23: 3. The contract in every language | C23: Concepts: Agent contract. Compare /invoke in Python (Sentinel), TypeScript (Liaison), Java (Notary), Go (Pulse).
B24: 4. The brain | C24: Conductor priority 1 files in this order: main.py, api/app.py, orchestration/pipeline.py, planner.py, executor.py, synthesizer.py, api/apps.py.
B25: 5. Security | C25: Filter Category = Security across all components. Then Request flow 3 (email approval).
B26: 6. Data and AI | C26: MCP server, Analyst's mcp_client, Librarian's rag/ folder, Pulse's holdings/.
B27: 7. The apps | C27: Web: main.tsx, App.tsx, api/client.ts, api/hooks.ts, pages/Dossier.tsx. Mobile: main.dart, api_client.dart, session.dart, household_screen.dart.
B28: 8. Tests | C28: Filter Category = Tests. For each component, read one test file and run the suite.
B30: Descriptions were written by reading each file. Folders like node_modules, .venv, target and the Flutter-generated android/ios/web folders are third-party or generated and are not listed file by file.

Sheet Components
A1: Component | B1: Language | C1: Framework | D1: Port | E1: Folder | F1: What it does | G1: Skills / endpoints | H1: Talks to | I1: Files | J1: Must-read files | K1: Read so far
A2: Conductor | B2: Python 3 | C2: FastAPI, httpx, Anthropic SDK | D2: 8000 | E2: agents/python/orchestrator | F2: The brain and the only door for the apps. Plans which agents to call (LLM or fallback rules), runs them in parallel stages, checks text with Sentinel, writes one answer. Also serves the app endpoints (sign-in, overview, skills, approve, live stream). | G2: POST /v1/chat; POST /invoke; /v1/auth/login; /v1/clients; /v1/clients/{id}/overview; /v1/skills/{agent}/{skill}; /v1/drafts/approve; /v1/stream | H2: All 9 agents (SERVICE_TOKEN); Anthropic API (planner/synthesizer); called by Atrium web and mobile (advisor JWT) | I2: =COUNTIF(Files!$B$2:$B$424,A2) -> 35 | J2: =COUNTIFS(Files!$B$2:$B$424,A2,Files!$F$2:$F$424,1) -> 13 | K2: =COUNTIFS(Files!$B$2:$B$424,A2,Files!$K$2:$K$424,"Yes") -> 0
A3: Librarian | B3: Python 3 | C3: FastAPI, ChromaDB | D3: 8001 | E3: agents/python/knowledge-rag | F3: RAG over the firm's documents: chunks and embeds policy/research files, retrieves the best passages and answers with numbered citations. Quarantines documents that contain prompt-injection text. | G3: search_knowledge; POST /v1/ingest; GET /v1/documents | H3: rag/ data and chroma-store; LLM optional; called by the Conductor | I3: =COUNTIF(Files!$B$2:$B$424,A3) -> 30 | J3: =COUNTIFS(Files!$B$2:$B$424,A3,Files!$F$2:$F$424,1) -> 9 | K3: =COUNTIFS(Files!$B$2:$B$424,A3,Files!$K$2:$K$424,"Yes") -> 0
A4: Analyst | B4: Python 3 | C4: FastAPI, MCP client | D4: 8002 | E4: agents/python/portfolio-insights | F4: Portfolio analysis: allocation vs target and drift, concentration, tax-loss ideas with replacements, rebalance actions. Reads holdings through the MCP server. | G4: analyze_portfolio | H4: MCP server :8500; called by the Conductor | I4: =COUNTIF(Files!$B$2:$B$424,A4) -> 29 | J4: =COUNTIFS(Files!$B$2:$B$424,A4,Files!$F$2:$F$424,1) -> 6 | K4: =COUNTIFS(Files!$B$2:$B$424,A4,Files!$K$2:$K$424,"Yes") -> 0
A5: Scribe | B5: Python 3 | C5: FastAPI | D5: 8003 | E5: agents/python/meeting-intel | F5: Reads meeting notes and pulls out the summary, action items with owners and dates, client concerns, life events and compliance flags (for example an SSN written in a note). | G5: summarize_meetings | H5: Meeting notes data; LLM optional; called by the Conductor | I5: =COUNTIF(Files!$B$2:$B$424,A5) -> 30 | J5: =COUNTIFS(Files!$B$2:$B$424,A5,Files!$F$2:$F$424,1) -> 5 | K5: =COUNTIFS(Files!$B$2:$B$424,A5,Files!$K$2:$K$424,"Yes") -> 0
A6: Sentinel | B6: Python 3 | C6: FastAPI | D6: 8004 | E6: agents/python/compliance-guard | F6: Security and compliance guard: detects prompt injection, masks PII, blocks non-compliant claims (for example 'guaranteed returns') and keeps an audit log. | G6: check_input; check_output; check_email | H6: Called by the Conductor before and after other agents | I6: =COUNTIF(Files!$B$2:$B$424,A6) -> 29 | J6: =COUNTIFS(Files!$B$2:$B$424,A6,Files!$F$2:$F$424,1) -> 9 | K6: =COUNTIFS(Files!$B$2:$B$424,A6,Files!$K$2:$K$424,"Yes") -> 0
A7: Herald | B7: TypeScript | C7: Node 22, Express 5 | D7: 8101 | E7: agents/node/client-comms | F7: Drafts client emails from CRM context and a template (or LLM), runs its own compliance rules and adds disclosures. Never sends: every draft requires approval. | G7: draft_email; review_email; GET /v1/rules | H7: Liaison :8102 for household context; called by the Conductor | I7: =COUNTIF(Files!$B$2:$B$424,A7) -> 28 | J7: =COUNTIFS(Files!$B$2:$B$424,A7,Files!$F$2:$F$424,1) -> 10 | K7: =COUNTIFS(Files!$B$2:$B$424,A7,Files!$K$2:$K$424,"Yes") -> 0
A8: Liaison | B8: TypeScript | C8: Node 22, Express 5 | D8: 8102 | E8: agents/node/crm-sync | F8: The CRM: households, members (PII masked), preferences, tasks and notes. Writes are idempotent (idempotency keys). | G8: get_household; list_tasks; log_note; GET /v1/households | H8: data/crm.json; called by the Conductor and Herald | I8: =COUNTIF(Files!$B$2:$B$424,A8) -> 27 | J8: =COUNTIFS(Files!$B$2:$B$424,A8,Files!$F$2:$F$424,1) -> 8 | K8: =COUNTIFS(Files!$B$2:$B$424,A8,Files!$K$2:$K$424,"Yes") -> 0
A9: Notary | B9: Java 21 | C9: Spring Boot 3.5 | D9: 8201 | E9: agents/java/onboarding-kyc | F9: KYC/onboarding: 14 rules over documents (expiring IDs, missing W-9, beneficiaries), fuzzy AML name screening against a fictional watchlist, idempotent document recording (stores only the last 4 digits). | G9: check_kyc; list_documents; screen_name; record_document | H9: data/kyc.seed.json, watchlist.json; called by the Conductor | I9: =COUNTIF(Files!$B$2:$B$424,A9) -> 42 | J9: =COUNTIFS(Files!$B$2:$B$424,A9,Files!$F$2:$F$424,1) -> 12 | K9: =COUNTIFS(Files!$B$2:$B$424,A9,Files!$K$2:$K$424,"Yes") -> 0
A10: Actuary | B10: Java 21 | C10: Spring Boot 3.5 | D10: 8202 | E10: agents/java/risk-engine | F10: Risk and planning: risk score (lower of willingness and capacity), seeded Monte Carlo retirement projections, historical stress tests. | G10: risk_score; project_retirement; stress_test | H10: MCP server :8500 (snapshot fallback); called by the Conductor | I10: =COUNTIF(Files!$B$2:$B$424,A10) -> 45 | J10: =COUNTIFS(Files!$B$2:$B$424,A10,Files!$F$2:$F$424,1) -> 12 | K10: =COUNTIFS(Files!$B$2:$B$424,A10,Files!$K$2:$K$424,"Yes") -> 0
A11: Pulse | B11: Go 1.22+ | C11: Standard library only | D11: 8301 | E11: agents/go/market-pulse | F11: Market events: matches news to each household's holdings, estimates dollar impact, ranks relevance, streams new events live (SSE). Quarantines injected 'news'. | G11: get_events; scan_clients; list_events; POST /v1/events; GET /v1/stream | H11: MCP server :8500; streams to the Conductor | I11: =COUNTIF(Files!$B$2:$B$424,A11) -> 31 | J11: =COUNTIFS(Files!$B$2:$B$424,A11,Files!$F$2:$F$424,1) -> 11 | K11: =COUNTIFS(Files!$B$2:$B$424,A11,Files!$K$2:$K$424,"Yes") -> 0
A12: MCP server | B12: Python 3 | C12: MCP SDK (streamable HTTP), uvicorn | D12: 8500 | E12: mcp-servers/advisor-tools | F12: Model Context Protocol server exposing read-only advisor tools (holdings, accounts, prices) to agents and LLMs, behind a service token. | G12: MCP tools over POST /mcp; /health | H12: Called by Analyst, Actuary and Pulse | I12: =COUNTIF(Files!$B$2:$B$424,A12) -> 14 | J12: =COUNTIFS(Files!$B$2:$B$424,A12,Files!$F$2:$F$424,1) -> 4 | K12: =COUNTIFS(Files!$B$2:$B$424,A12,Files!$K$2:$K$424,"Yes") -> 0
A13: RAG data | B13: Markdown | E13: rag | F13: The firm's sample documents the Librarian indexes (policies, research notes). | H13: Read by the Librarian's ingest | I13: =COUNTIF(Files!$B$2:$B$424,A13) -> 8 | J13: =COUNTIFS(Files!$B$2:$B$424,A13,Files!$F$2:$F$424,1) -> 0 | K13: =COUNTIFS(Files!$B$2:$B$424,A13,Files!$K$2:$K$424,"Yes") -> 0
A14: Atrium web | B14: TypeScript | C14: React 19, Vite, TanStack Query | D14: 5173 | E14: frontend/web | F14: The advisor workstation in the browser: households, the dossier (six agents in parallel), retirement what-if, email draft and approve, Ask, live market news. | G14: Uses Conductor /v1/* only | H14: Conductor :8000 (via the Vite proxy) | I14: =COUNTIF(Files!$B$2:$B$424,A14) -> 35 | J14: =COUNTIFS(Files!$B$2:$B$424,A14,Files!$F$2:$F$424,1) -> 12 | K14: =COUNTIFS(Files!$B$2:$B$424,A14,Files!$K$2:$K$424,"Yes") -> 0
A15: Atrium mobile | B15: Dart | C15: Flutter 3 | E15: frontend/mobile | F15: The same advisor experience on Android, iOS and Chrome: households, household file, email approve, live news tab, Ask. | G15: Uses Conductor /v1/* only | H15: Conductor :8000 (10.0.2.2 from the Android emulator) | I15: =COUNTIF(Files!$B$2:$B$424,A15) -> 34 | J15: =COUNTIFS(Files!$B$2:$B$424,A15,Files!$F$2:$F$424,1) -> 6 | K15: =COUNTIFS(Files!$B$2:$B$424,A15,Files!$K$2:$K$424,"Yes") -> 0
A16: Repo scripts | B16: PowerShell | E16: scripts | F16: Repo-wide helper scripts (for example creating aurelius/.env with generated secrets). | I16: =COUNTIF(Files!$B$2:$B$424,A16) -> 1 | J16: =COUNTIFS(Files!$B$2:$B$424,A16,Files!$F$2:$F$424,1) -> 0 | K16: =COUNTIFS(Files!$B$2:$B$424,A16,Files!$K$2:$K$424,"Yes") -> 0
A17: Repo root | E17: (top level) | F17: Placeholder folders reserved for later (contracts, docs, infra, security, tests). | I17: =COUNTIF(Files!$B$2:$B$424,A17) -> 5 | J17: =COUNTIFS(Files!$B$2:$B$424,A17,Files!$F$2:$F$424,1) -> 0 | K17: =COUNTIFS(Files!$B$2:$B$424,A17,Files!$K$2:$K$424,"Yes") -> 0
A18: Total | I18: =SUM(I2:I17) -> 423 | J18: =SUM(J2:J17) -> 117 | K18: =SUM(K2:K17) -> 0

Sheet Request flows
A1: Five real requests, followed file by file
A2: Each step names the file that does it. Find the file on the Files sheet for the details.
A4: 1. Sign in
A5: Step | B5: What happens | C5: Component | D5: File
A6: 1 | B6: Advisor types the password and presses Sign in | C6: Atrium web | D6: frontend/web/src/pages/SignIn.tsx
A7: 2 | B7: auth.signIn calls the API client | C7: Atrium web | D7: frontend/web/src/lib/auth.tsx
A8: 3 | B8: POST /v1/auth/login is sent (Vite proxies it to :8000) | C8: Atrium web | D8: frontend/web/src/api/client.ts
A9: 4 | B9: Conductor checks DEV_LOGIN_PASSWORD (constant-time), throttles failures, returns a signed JWT | C9: Conductor | D9: agents/python/orchestrator/src/api/apps.py
A10: 5 | B10: JWT is created and later verified on every request | C10: Conductor | D10: agents/python/orchestrator/src/security/auth.py
A11: 6 | B11: Token is kept in sessionStorage; an expiry timer signs out on time | C11: Atrium web | D11: frontend/web/src/lib/auth.tsx
A13: 2. Open a household (the dossier)
A14: Step | B14: What happens | C14: Component | D14: File
A15: 1 | B15: Advisor clicks a household; the page asks for the overview | C15: Atrium web | D15: frontend/web/src/pages/Dossier.tsx
A16: 2 | B16: useOverview calls GET /v1/clients/{id}/overview | C16: Atrium web | D16: frontend/web/src/api/hooks.ts
A17: 3 | B17: Conductor runs 6 skills in parallel (asyncio.gather) and times each | C17: Conductor | D17: agents/python/orchestrator/src/api/apps.py
A18: 4 | B18: Each call goes out with SERVICE_TOKEN and X-Trace-Id (or to recorded answers in mock mode) | C18: Conductor | D18: agents/python/orchestrator/src/orchestration/executor.py
A19: 5 | B19: Liaison returns the household from the CRM | C19: Liaison | D19: agents/node/crm-sync/src/skills/index.ts
A20: 6 | B20: Analyst asks the MCP server for holdings and analyses them | C20: Analyst | D20: agents/python/portfolio-insights/src/analysis/engine.py
A21: 7 | B21: MCP server serves holdings from its data store | C21: MCP server | D21: mcp-servers/advisor-tools/src/server.py
A22: 8 | B22: Notary applies the KYC rules | C22: Notary | D22: agents/java/onboarding-kyc/src/main/java/com/aurelius/notary/kyc/KycRules.java
A23: 9 | B23: Actuary scores risk | C23: Actuary | D23: agents/java/risk-engine/src/main/java/com/aurelius/actuary/risk/RiskScorer.java
A24: 10 | B24: Pulse matches recent events to the holdings | C24: Pulse | D24: agents/go/market-pulse/internal/impact/impact.go
A25: 11 | B25: Scribe summarises the meetings | C25: Scribe | D25: agents/python/meeting-intel/src/extract/service.py
A26: 12 | B26: Web builds 'Needs you' from the six answers and renders each section | C26: Atrium web | D26: frontend/web/src/components/NeedsYou.tsx
A28: 3. Draft, edit and approve an email
A29: Step | B29: What happens | C29: Component | D29: File
A30: 1 | B30: Advisor clicks Draft email | C30: Atrium web | D30: frontend/web/src/components/EmailComposer.tsx
A31: 2 | B31: POST /v1/skills/herald/draft_email; the Conductor checks the read-only allowlist | C31: Conductor | D31: agents/python/orchestrator/src/api/apps.py
A32: 3 | B32: Herald fetches household context from the Liaison | C32: Herald | D32: agents/node/client-comms/src/clients/liaison.ts
A33: 4 | B33: Herald composes the draft from a template (or LLM) | C33: Herald | D33: agents/node/client-comms/src/compose/composer.ts
A34: 5 | B34: Herald's compliance rules fix risky phrases and add disclosures | C34: Herald | D34: agents/node/client-comms/src/compose/compliance.ts
A35: 6 | B35: Advisor edits; Approve stays disabled while [placeholders] remain | C35: Atrium web | D35: frontend/web/src/components/EmailComposer.tsx
A36: 7 | B36: POST /v1/drafts/approve: Sentinel re-checks the edited text | C36: Conductor | D36: agents/python/orchestrator/src/security/guardrails.py
A37: 8 | B37: Sentinel's rules detect non-compliant claims and PII | C37: Sentinel | D37: agents/python/compliance-guard/src/guards/engine.py
A38: 9 | B38: If clean, Liaison logs a CRM note (subject + fingerprint, idempotent) | C38: Liaison | D38: agents/node/crm-sync/src/store/crmStore.ts
A40: 4. Live market news
A41: Step | B41: What happens | C41: Component | D41: File
A42: 1 | B42: Workspace opens the stream after sign-in | C42: Atrium web | D42: frontend/web/src/pages/Workspace.tsx
A43: 2 | B43: fetch() reads SSE with an Authorization header and reconnects with backoff | C43: Atrium web | D43: frontend/web/src/api/stream.ts
A44: 3 | B44: Conductor relays Pulse's stream (30-minute limit, heartbeats) | C44: Conductor | D44: agents/python/orchestrator/src/api/apps.py
A45: 4 | B45: A news item is POSTed to Pulse /v1/events | C45: Pulse | D45: agents/go/market-pulse/internal/api/server.go
A46: 5 | B46: Pulse quarantines prompt-injection text | C46: Pulse | D46: agents/go/market-pulse/internal/events/guard.go
A47: 6 | B47: Pulse's broker fans the event out to subscribers with backpressure | C47: Pulse | D47: agents/go/market-pulse/internal/events/broker.go
A48: 7 | B48: The headline appears in the rail (web) or News tab (mobile) | C48: Atrium mobile | D48: frontend/mobile/lib/state/news_controller.dart
A50: 5. Ask Aurelius (free-form question)
A51: Step | B51: What happens | C51: Component | D51: File
A52: 1 | B52: Advisor asks a question | C52: Atrium web | D52: frontend/web/src/components/AskPanel.tsx
A53: 2 | B53: POST /v1/chat | C53: Conductor | D53: agents/python/orchestrator/src/api/app.py
A54: 3 | B54: Sentinel checks the question for injection and PII | C54: Conductor | D54: agents/python/orchestrator/src/security/guardrails.py
A55: 4 | B55: Planner chooses agents and stages (Claude, or fallback rules without a key) | C55: Conductor | D55: agents/python/orchestrator/src/orchestration/planner.py
A56: 5 | B56: Executor runs each stage in parallel | C56: Conductor | D56: agents/python/orchestrator/src/orchestration/executor.py
A57: 6 | B57: Librarian retrieves cited passages from the firm's documents | C57: Librarian | D57: agents/python/knowledge-rag/src/rag/retriever.py
A58: 7 | B58: Synthesizer writes one answer; Sentinel checks it; disclosure added | C58: Conductor | D58: agents/python/orchestrator/src/orchestration/synthesizer.py
A59: 8 | B59: The whole sequence is wired together here | C59: Conductor | D59: agents/python/orchestrator/src/orchestration/pipeline.py

Sheet Concepts
A1: Concept | B1: What it means here | C1: Where to look
A2: Agent contract | B2: Every agent exposes POST /invoke {skill, input, context{trace_id,user_id,client_id}} -> {agent,status,output,error}, plus /health and /.well-known/agent.json. The Conductor can treat a Python, TypeScript, Java or Go agent identically. | C2: orchestrator/src/schemas/models.py; crm-sync/src/contract.ts; notary .../web/AgentController.java; market-pulse/internal/contract/contract.go
A3: Service token | B3: Agents only accept calls carrying SERVICE_TOKEN (compared in constant time; agents refuse to start if it is shorter than 24 characters). Apps never see it. | C3: */security/auth.py; crm-sync/src/auth.ts; */web/ServiceTokenFilter.java; market-pulse/internal/api/server.go
A4: Advisor JWT | B4: Apps sign in to the Conductor and send a short-lived signed JWT; 401 or expiry signs out. | C4: orchestrator/src/security/auth.py; web/src/lib/auth.tsx; mobile/lib/state/session.dart
A5: Trace ID | B5: X-Trace-Id travels from the app through the Conductor to every agent and back, so one request can be followed across all logs and languages. | C5: */TraceFilter.java; */log_setup.py; web/src/api/client.ts
A6: Guardrails (Sentinel) | B6: Inputs are checked for prompt injection and PII; outputs and emails are checked for non-compliant claims. Text can be blocked or rewritten. | C6: compliance-guard/src/guards/*; orchestrator/src/security/guardrails.py
A7: Human in the loop | B7: Agents draft; only an advisor approval logs anything to the CRM; nothing is ever sent automatically. | C7: client-comms/src/compose/*; orchestrator/src/api/apps.py (approve); web EmailComposer.tsx; mobile email_screen.dart
A8: MCP | B8: Model Context Protocol: a standard way to expose tools/data to LLMs and agents. Here, holdings data over streamable HTTP with a session id. | C8: mcp-servers/advisor-tools/src/server.py; portfolio-insights/src/mcp_client/client.py; actuary .../mcp/McpClient.java; market-pulse/internal/holdings/mcp.go
A9: RAG | B9: Retrieval-augmented generation: chunk documents, embed, retrieve the nearest passages, answer only from them with citations. | C9: knowledge-rag/src/rag/*
A10: Planner / executor / synthesizer | B10: The Conductor's orchestration pattern: plan stages, run each stage's steps in parallel, merge results into one answer. | C10: orchestrator/src/orchestration/*
A11: Mock mode and recorded answers | B11: MOCK_AGENTS=true replays real recorded agent outputs, so the Conductor and apps run without all ten services. REAL_AGENTS lists exceptions. | C11: orchestrator/src/agents/mock_agents.py; recorded_responses.json
A12: Server-Sent Events (SSE) | B12: One long HTTP response carrying 'event:' and 'data:' blocks; used for live market news end to end. | C12: market-pulse/internal/api/server.go; orchestrator apps.py (/v1/stream); web/src/api/stream.ts; mobile/lib/api/sse.dart
... A15: Testing approach | B15: Every component has unit and API tests; frontends test against a fake Conductor replaying real recorded outputs. | C15: */tests/*; frontend/web/tests; frontend/mobile/test

Sheet Files
A1: # | B1: Component | C1: Folder | D1: File | E1: Category | F1: Priority | G1: What it does | H1: Key parts | I1: Connects to | J1: How to explain it in an interview | K1: Read it? (Yes/No)
A2: 1 | B2: Conductor | C2: agents/python/orchestrator/src/agents | D2: registry.py | E2: Business logic | F2: 1 | G2: Hard-coded registry of the nine agents with URLs and skill descriptions, plus the UI skill allowlist. | H2: AgentInfo; build_registry(); UI_SKILLS (read-only skills apps may call); describe_for_planner(); sentinel plannable=False | I2: used by planner.py, executor.py, apps.py, api/app.py | J2: The planner prompt is built from this registry, and a separate allowlist keeps write skills out of reach of the apps. | K2: No
A3: 2 | B3: Conductor | C3: agents/python/orchestrator/src/api | D3: app.py | E3: API / routes | F3: 1 | G3: Creates the FastAPI app: lifespan wiring of the pipeline, CORS, security headers, error handler, and the core endpoints (health, agent card, agents list, chat, invoke). | H3: create_app(); GET /health; GET /.well-known/agent.json; GET /v1/agents (up/down/mock); POST /v1/chat (advisor JWT); POST /invoke (service token, skill 'chat'); security_headers middleware; _run maps guardrail errors to 400/503 | I3: called by main.py; includes api/apps.py router; uses Pipeline, Planner, Synthesizer, Guardrails, AgentClient, security/auth.py | J3: The global exception handler returns only a trace id, never a stack trace, and the app refuses to start with insecure settings. | K3: No
A4: 3 | B4: Conductor | C4: agents/python/orchestrator/src/api | D4: apps.py | E4: API / routes | F4: 1 | G4: Backend-for-frontend endpoints shaped for the Atrium web and Flutter mobile screens, so apps never hold the service token. | H4: POST /v1/auth/login (dev password, 5 fails per 5 min throttle); GET /v1/me; GET /v1/clients; GET /v1/clients/{id}/overview (6 agents via asyncio.gather); POST /v1/skills/{agent}/{skill} (allowlist); POST /v1/drafts/approve; GET /v1/stream (SSE relay of Pulse) | I4: included by api/app.py; calls AgentClient, UI_SKILLS in agents/registry.py, Sentinel via guardrails, Liaison log_note, Pulse :8301 | J4: Skill calls go through an explicit read-only allowlist and approvals re-check text with Sentinel and log only a hash, keeping a human in the loop. | K4: No
A5: 4 | B5: Conductor | C5: agents/python/orchestrator/src/core | D5: config.py | E5: Config | F5: 1 | G5: Typed settings loaded from environment and .env files via pydantic-settings: ports, agent URLs, LLM model, auth, limits, mock flags. | H5: Settings; MOCK_AGENTS; REAL_AGENTS; SENTINEL_FAIL_MODE; JWT_SIGNING_KEY; SERVICE_TOKEN; ALLOWED_ORIGINS; DEV_LOGIN_PASSWORD; max_plan_stages=4, max_plan_steps=8; use_mock_llm; is_mocked(); get_settings() | I5: used by nearly every file in src/; reads root .env then orchestrator .env | J5: Typed settings fail at startup on bad values and keep secrets and URLs out of code. | K5: No
A6: 5 | B6: Conductor | C6: agents/python/orchestrator/src/llm | D6: client.py | E6: Data access / clients | F6: 1 | G6: The only file that talks to Claude: a thin gateway with mock mode, timeouts, retries, prompt caching and cost logging. | H6: LLMClient.complete(); complete_with_tool() forces tool_choice; _system_blocks with cache_control; _estimate_cost price table; LLMError; max_retries=2 | I6: used by planner.py and synthesizer.py; created in api/app.py | J6: One gateway lets you swap models by env var, log token cost in one place, and test without an API key. | K6: No
A7: 6 | B7: Conductor | C7: agents/python/orchestrator/src | D7: main.py | E7: Entry point | F7: 1 | G7: Starts the Conductor with uvicorn on port 8000. Builds the FastAPI app through a factory function so reload works. | H7: build_app() sets up JSON logging and calls create_app(); __main__ runs uvicorn with reload=True, host from CONDUCTOR_HOST | I7: calls api/app.py create_app, core/config.py, core/log_setup.py | J7: Binding to 127.0.0.1 by default keeps the API private to the machine unless CONDUCTOR_HOST is changed. | K7: No
A8: 7 | B8: Conductor | C8: agents/python/orchestrator/src/orchestration | D8: executor.py | E8: Business logic | F8: 1 | G8: Runs a Plan: stages in order, steps within a stage in parallel, each call isolated, with service-token auth, retry and mock switch. | H8: AgentClient.call() (POST {agent}/invoke, 1 retry on 5xx/timeouts, no retry on 4xx); _run_step; run_plan() with asyncio.gather; prior_results passed to later stages | I8: used by pipeline.py, apps.py, guardrails.py; calls agents on their ports or mock_agents | J8: One failing agent returns an error result instead of breaking the whole request, and only transient errors are retried. | K8: No
A9: 8 | B9: Conductor | C9: agents/python/orchestrator/src/orchestration | D9: pipeline.py | E9: Business logic | F9: 1 | G9: Runs the 7-phase request flow: input guard, plan, execute, drafts, synthesize, output guard, return. | H9: Pipeline.handle(); builds InvokeContext with trace id; logs ids not text; Herald output becomes a Draft after output guard | I9: called by api/app.py _run; calls Guardrails, Planner, run_plan, Synthesizer | J9: Sentinel masks PII before the planner or LLM sees the message, so the model never receives raw sensitive data. | K9: No
A10: 9 | B10: Conductor | C10: agents/python/orchestrator/src/orchestration | D10: planner.py | E10: Business logic | F10: 1 | G10: Turns an advisor request into a staged Plan using Claude with a forced tool call, validates it, and falls back to keyword rules if the LLM fails. | H10: PLANNER_SYSTEM prompt; _plan_tool (submit_plan); validate_plan() drops unknown agents/skills, caps size, forces UI client_id; _RULES and rule_based_plan(); Planner.plan() | I10: called by pipeline.py; uses llm/client.py and agents/registry.py | J10: The LLM proposes and code decides: validate_plan filters the plan, and rules give graceful degradation. | K10: No
A11: 10 | B11: Conductor | C11: agents/python/orchestrator/src/orchestration | D11: synthesizer.py | E11: Business logic | F11: 1 | G11: Merges agent results into a short Markdown briefing for the advisor, with a non-LLM fallback. | H11: SYNTH_SYSTEM prompt (use only agent facts, cite [Agent]); _fallback_answer(); Synthesizer.synthesize(); Herald body not sent to the LLM | I11: called by pipeline.py; uses llm/client.py | J11: Grounding the answer in agent output and citing the source agent reduces invented numbers, which matters in finance. | K11: No
A12: 11 | B12: Conductor | C12: agents/python/orchestrator/src/schemas | D12: models.py | E12: Models / schemas | F12: 1 | G12: Pydantic models: the agent contract shared by all agents, plus planning, results and the chat API types. | H12: AgentRequest/AgentResponse/InvokeContext (POST /invoke contract); PlanStep/Plan (stages of parallel steps); StepResult; ChatRequest (client_id regex, 20000 char cap); Draft (requires_approval); ChatResponse | I12: used by executor, planner, pipeline, apps, mock_agents and api/app.py | J12: One JSON contract for all ten agents, in four languages, lets the Conductor call any of them identically. | K12: No
A13: 12 | B13: Conductor | C13: agents/python/orchestrator/src/security | D13: auth.py | E13: Security | F13: 1 | G13: JWT verification for advisors, constant-time shared-token check for agent callers, and startup security checks. | H13: create_token (HS256); require_user (pins algorithm, checks exp/sub/iss/aud, role advisor or admin); require_service (hmac.compare_digest); check_startup_security | I13: used by api/app.py and api/apps.py Depends | J13: Two credential types for two caller types, with a fail-closed startup check that rejects weak keys and wildcard CORS. | K13: No
A14: 13 | B14: Conductor | C14: agents/python/orchestrator/src/security | D14: guardrails.py | E14: Security | F14: 1 | G14: Wraps Sentinel calls for input and output checks and decides what happens if Sentinel is down. | H14: Guardrails.check_input/check_output; GuardrailBlocked; GuardrailUnavailable; SENTINEL_FAIL_MODE closed (default) or open | I14: called by pipeline.py and apps.py; calls Sentinel :8004 via AgentClient | J14: Fail closed: if the security check cannot run, the request is refused rather than skipped. | K14: No
A15: 14 | B15: Conductor | C15: agents/python/orchestrator | D15: run.ps1 | E15: Build / tooling | F15: 2 | G15: Windows script that sets up .env, creates the venv, installs deps, then starts the server or runs tests (-Test). | H15: calls scripts/setup_env.ps1; .venv; src/main.py; pytest | I15: uses repo scripts/setup_env.ps1 | K15: No
A16: 15 | B16: Conductor | C16: agents/python/orchestrator/src/agents | D16: mock_agents.py | E16: Business logic | F16: 2 | G16: Test double that answers for agents when MOCK_AGENTS=true: a regex-based Sentinel and recorded real outputs for the rest. | H16: mask_pii (SSN, account number, email, phone); _INJECTION_PATTERNS; _sentinel(); _recorded(); _write() for liaison.log_note; respond() with 50 ms fake latency | I16: called by executor.py AgentClient and apps.py; reads recorded_responses.json | J16: Mocks replay real recorded agent output, so code written against them works unchanged on the real agents. | K16: No
A17: 16 | B17: Conductor | C17: agents/python/orchestrator/tests | D17: conftest.py | E17: Tests | F17: 2 | G17: Shared fixtures: settings with fake LLM and agents, a TestClient, and an auth header. | H17: settings; client; auth | I17: used by all tests | J17: Tests ignore the real .env, so they are fast, free and deterministic. | K17: No
A18: 17 | B18: Conductor | C18: agents/python/orchestrator/tests | D18: test_api.py | E18: Tests | F18: 2 | G18: End-to-end tests of core API: auth, headers, full chat flow, PII masking, injection blocking, limits, invoke, fail-closed. | H18: test_rejects_forged_token; test_rejects_expired_token; test_meeting_prep_full_flow; test_pii_is_masked; test_prompt_injection_blocked; test_fail_closed_when_sentinel_down; test_refuses_to_start_with_weak_jwt_key | I18: tests api/app.py and the pipeline | J18: Security behaviors are tested as features, including forged and expired tokens and Sentinel outage. | K18: No
A19: 18 | B19: Conductor | C19: agents/python/orchestrator/tests | D19: test_apps.py | E19: Tests | F19: 2 | G19: Tests the app-facing endpoints: login throttle, overview parallelism, allowlist, draft approval, SSE stream, CORS. | H19: test_login_is_throttled_after_5_failures; test_overview_survives_one_agent_down; test_writes_and_unknown_skills_are_refused; test_approval_refused_if_sentinel_changes_the_text; test_stream_says_hello_pings_and_ends_at_its_time_limit | I19: tests api/apps.py | J19: Resilience is tested: the overview still returns when one agent is down. | K19: No
A20: 19 | B20: Conductor | C20: agents/python/orchestrator/tests | D20: test_planner_executor.py | E20: Tests | F20: 2 | G20: Unit tests for plan validation, rule-based planning and the executor's parallelism and isolation. | H20: test_validate_plan_drops_bad_steps; test_validate_plan_caps_size; test_stage_runs_in_parallel; test_one_failing_agent_does_not_break_others; test_later_stage_receives_prior_results | I20: tests planner.py and executor.py | J20: Parallelism is proven by timing, not assumed. | K20: No
A21: 20 | B21: Conductor | C21: agents/python/orchestrator | D21: .env.example | E21: Config | F21: 3 | G21: Template of Conductor environment variables with comments. | H21: ANTHROPIC_API_KEY; LLM_MODEL; MOCK_AGENTS; REAL_AGENTS=sentinel; SERVICE_TOKEN; AUTH_REQUIRED; JWT_SIGNING_KEY; ALLOWED_ORIGINS; DEV_LOGIN_PASSWORD; SENTINEL_FAIL_MODE | I21: read as reference for core/config.py | J21: Placeholders are rejected at startup, so the template cannot be run insecurely by accident. | K21: No
A22: 21 | B22: Conductor | C22: agents/python/orchestrator | D22: README.md | E22: Docs | F22: 3 | G22: Overview of the Conductor: request flow, folder map, endpoints, modes and security principles. | K22: No
A23: 22 | B23: Conductor | C23: agents/python/orchestrator | D23: TESTING.md | E23: Docs | F23: 3 | G23: Runbook for starting, getting tokens, firing requests, running tests, plus troubleshooting and modes. | K23: No
A24: 23 | B24: Conductor | C24: agents/python/orchestrator | D24: api-tests.http | E24: Tests | F24: 3 | G24: Manual request collection for the VS Code REST Client, covering public, auth, chat, invoke and app endpoints with expected results in comments. | H24: sections: public endpoints, authentication, chat, invoke, apps; @token and @serviceToken variables | I24: hits the running Conductor on :8000 | K24: No
A25: 24 | B25: Conductor | C25: agents/python/orchestrator | D25: pytest.ini | E25: Build / tooling | F25: 3 | G25: Pytest config: puts src on the import path and sets tests folder. | H25: pythonpath=src; testpaths=tests | I25: used by pytest | K25: No
A26: 25 | B26: Conductor | C26: agents/python/orchestrator | D26: requirements.txt | E26: Build / tooling | F26: 3 | G26: Python dependencies for the Conductor. | H26: fastapi; uvicorn; pydantic; pydantic-settings; httpx; anthropic; PyJWT; pytest | I26: installed by run.ps1 | K26: No
A27: 26 | B27: Conductor | C27: agents/python/orchestrator/scripts | D27: make_dev_token.py | E27: Build / tooling | F27: 3 | G27: Prints a short-lived advisor JWT for local testing. | H27: argv user and minutes; uses create_token | I27: uses core/config.py and security/auth.py | K27: No
A28: 27 | B28: Conductor | C28: agents/python/orchestrator/src/agents | D28: __init__.py | E28: Business logic | F28: 3 | G28: Empty package marker. | K28: No
A29: 28 | B29: Conductor | C29: agents/python/orchestrator/src/agents | D29: recorded_responses.json | E29: Test data | F29: 3 | G29: Real outputs captured from the running agents for the three demo households, used by the mocks. | H29: keys like liaison.get_household, analyst.analyze_portfolio, notary.check_kyc, actuary.stress_test, pulse.get_events, librarian.search_knowledge, herald.draft_email, each by client_id or '*' | I29: read by agents/mock_agents.py and api/apps.py /v1/clients | K29: No
A30: 29 | B30: Conductor | C30: agents/python/orchestrator/src/api | D30: __init__.py | E30: API / routes | F30: 3 | G30: Empty package marker. | K30: No
A31: 30 | B31: Conductor | C31: agents/python/orchestrator/src/core | D31: __init__.py | E31: Config | F31: 3 | G31: Empty package marker. | K31: No
A32: 31 | B32: Conductor | C32: agents/python/orchestrator/src/core | D32: log_setup.py | E32: Config | F32: 3 | G32: Switches logging to one JSON object per line on stdout so logs can be searched by trace id. | H32: JsonFormatter; setup_logging(); quiets httpx logs | I32: called by main.py | J32: Logging ids, counts and timings but never message text avoids leaking PII into logs. | K32: No
A33: 32 | B33: Conductor | C33: agents/python/orchestrator/src/llm | D33: __init__.py | E33: Business logic | F33: 3 | G33: Empty package marker. | K33: No
A34: 33 | B34: Conductor | C34: agents/python/orchestrator/src/orchestration | D34: __init__.py | E34: Business logic | F34: 3 | G34: Empty package marker. | K34: No
A35: 34 | B35: Conductor | C35: agents/python/orchestrator/src/schemas | D35: __init__.py | E35: Models / schemas | F35: 3 | G35: Empty package marker. | K35: No
A36: 35 | B36: Conductor | C36: agents/python/orchestrator/src/security | D36: __init__.py | E36: Security | F36: 3 | G36: Empty package marker. | K36: No
A37: 36 | B37: Librarian | C37: agents/python/knowledge-rag/src/api | D37: app.py | E37: API / routes | F37: 1 | G37: Builds the Librarian FastAPI app. /invoke runs the search_knowledge skill (retrieve then answer); extra endpoints expose raw search, index contents and re-ingestion. | H37: GET /health (chunks_indexed); GET /.well-known/agent.json; POST /invoke; POST /v1/search (no LLM, shows scores); GET /v1/documents; POST /v1/ingest (asyncio lock); lifespan auto-ingests when index empty | I37: calls rag/retriever.py, rag/ingest.py, rag/store.py, llm/answerer.py, security/auth.py; called by the Conductor | J37: Blocking Chroma and embedding work runs in asyncio.to_thread and ingestion is serialized with a lock, so the event loop stays responsive. | K37: No
A38: 37 | B38: Librarian | C38: agents/python/knowledge-rag/src/llm | D38: answerer.py | E38: Business logic | F38: 1 | G38: Step 6 of RAG: Claude Haiku writes a grounded answer from numbered passages in <document> tags, citing [n]. Code then validates citations; without a key or on failure it falls back to an extractive answer of quoted passages. | H38: SYSTEM prompt (use only documents, cite, max 150 words); NOT_FOUND; Answerer.answer(); _extractive(); _citations(); prompt caching on the system block | I38: called by api/app.py invoke(); reads core/config.py | J38: Never trust model output format: only [n] citations that really exist are kept, and passages are treated as untrusted data. | K38: No
A39: 38 | B39: Librarian | C39: agents/python/knowledge-rag/src | D39: main.py | E39: Entry point | F39: 1 | G39: Starts the Librarian with uvicorn on 127.0.0.1:8001 via an app factory; on first start the index is empty so the docs folder is ingested automatically. | H39: build_app() sets up logging and calls create_app(); __main__ runs uvicorn with settings.port | I39: imports api/app.py, core/config.py, core/log_setup.py | K39: No
A40: 39 | B40: Librarian | C40: agents/python/knowledge-rag/src/rag | D40: chunker.py | E40: Business logic | F40: 1 | G40: Step 2 of RAG: splits documents on markdown headings, packs paragraphs into about 700-character chunks with overlap, and prefixes each chunk with 'Title > Section'. | H40: Chunk dataclass; _sections(); _pack(); chunk_document(); chunk id = sha1(source#index)[:16]; empty headings carried into the next chunk | I40: called by rag/ingest.py; uses rag/loader.py Document | J40: Stable chunk ids make re-ingestion replace rather than duplicate, and heading carry-over keeps facts like 'Rating: Hold'. | K40: No
A41: 40 | B41: Librarian | C41: agents/python/knowledge-rag/src/rag | D41: ingest.py | E41: Business logic | F41: 1 | G41: Ingestion pipeline load, chunk, safety check, embed, store. It is idempotent: old chunks of a document are deleted first and documents removed from disk are removed from the index. | H41: run_ingest() returns IngestReport (documents, chunks, quarantined, removed_sources, duration_ms) | I41: called by api/app.py (startup and POST /v1/ingest) and scripts/ingest.py; uses loader, chunker, safety, embeddings, store | J41: Idempotent ingestion means an edited policy never leaves stale passages behind. | K41: No
A42: 41 | B42: Librarian | C42: agents/python/knowledge-rag/src/rag | D42: retriever.py | E42: Business logic | F42: 1 | G42: Step 5 of RAG: embeds the question, fetches nearest chunks, drops anything below the minimum similarity, keeps the best chunk per source-section, and returns the top K. | H42: Retriever.retrieve(query, top_k, doc_type); fetches 3x top_k candidates | I42: called by api/app.py invoke(); uses rag/store.py and embeddings.py | J42: The minimum-score cutoff is an anti-hallucination tool: if nothing is close enough, nothing is returned and the answer says not found. | K42: No
A43: 42 | B43: Librarian | C43: agents/python/knowledge-rag/src/rag | D43: safety.py | E43: Security | F43: 1 | G43: Ingest-time defense against indirect prompt injection: any chunk that looks like instructions to the AI is quarantined and never indexed. | H43: _PATTERNS (override instructions, role change, mentions system prompt, orders to advisors); check_chunk() returns a reason or None | I43: called by rag/ingest.py; tested in tests/test_pipeline.py | J43: Poisoned documents are the RAG-specific attack, so suspicious chunks are stopped before they can be retrieved. | K43: No
A44: 43 | B44: Librarian | C44: agents/python/knowledge-rag/src/rag | D44: store.py | E44: Data access / clients | F44: 1 | G44: Step 4 of RAG: wraps an embedded ChromaDB persistent collection (cosine space) for upsert, delete by source, list sources, and nearest-neighbour search. | H44: VectorStore: upsert(); delete_source(); sources(); search() with optional doc_type filter; Hit dataclass (score = 1 - distance) | I44: called by rag/ingest.py, rag/retriever.py, api/app.py; persists to rag/chroma-store | J44: Chroma runs embedded so there is no server to install, and the code would change little for a hosted vector DB. | K44: No
A45: 44 | B45: Librarian | C45: agents/python/knowledge-rag/src/schemas | D45: models.py | E45: Models / schemas | F45: 1 | G45: Pydantic models: the shared agent contract plus the Librarian's skill input and result types. | H45: SearchInput (query, top_k 1-10, doc_type); Citation; SearchResult (answer, grounded, citations, answered_by); IngestReport; DocType literal | I45: used by api/app.py, llm/answerer.py, rag/ingest.py | K45: No
A46: 45 | B46: Librarian | C46: agents/python/knowledge-rag/scripts | D46: ingest.py | E46: Build / tooling | F46: 2 | G46: Command-line script that rebuilds the knowledge index without starting the server and prints the ingest report as JSON. | H46: adds src to sys.path; run_ingest(settings, VectorStore, embedder) | I46: uses rag/ingest.py, rag/store.py, core/config.py | K46: No
A47: 46 | B47: Librarian | C47: agents/python/knowledge-rag/src/core | D47: config.py | E47: Config | F47: 2 | G47: Pydantic Settings for the Librarian: port, token, LLM settings, embedding provider, docs and Chroma folders, chunking and retrieval knobs. | H47: Settings: port 8001 (LIBRARIAN_PORT); embedding_provider minilm|hash; docs_dir rag/data/sample-docs; chroma_dir rag/chroma-store; chunk_size 700; chunk_overlap 120; top_k 4; collection_name per provider; effective_min_score .30 minilm / .12 hash | I47: used by all modules; REPO_ROOT is resolved from the file path | J47: The collection name includes the embedding provider because vectors from different models cannot be mixed. | K47: No
A48: 47 | B48: Librarian | C48: agents/python/knowledge-rag/src/rag | D48: embeddings.py | E48: Business logic | F48: 2 | G48: Step 3 of RAG: turns text into vectors. Two providers: minilm (all-MiniLM-L6-v2 via Chroma ONNX, semantic) and hash (offline feature hashing, word overlap only). | H48: Embedder Protocol; HashEmbedder (512 dims, stopwords, tiny stemmer, bigrams); MiniLMEmbedder; build_embedder() | I48: used by api/app.py, rag/ingest.py, rag/retriever.py; tests use hash | J48: The hash fallback lets tests and offline runs work with no model download. | K48: No
A49: 48 | B49: Librarian | C49: agents/python/knowledge-rag/src/rag | D49: loader.py | E49: Data access / clients | F49: 2 | G49: Step 1 of RAG: reads .md and .txt files from the docs folder and parses the front matter (title, doc_type, effective_date) into Document objects. | H49: Document dataclass; parse_front_matter(); load_documents() skips hidden and unsupported files | I49: called by rag/ingest.py; reads rag/data/sample-docs | J49: Metadata is kept with the text so answers can cite document and date and searches can filter by type. | K49: No
A50: 49 | B50: Librarian | C50: agents/python/knowledge-rag/src/security | D50: auth.py | E50: Security | F50: 2 | G50: Service-token authentication for protected endpoints, with a startup check that refuses weak tokens. Same pattern as Sentinel. | H50: require_service() with hmac.compare_digest; check_startup_security() | I50: used by api/app.py | J50: Constant-time comparison and fail-closed startup check. | K50: No
A51: 50 | B51: Librarian | C51: agents/python/knowledge-rag/tests | D51: conftest.py | E51: Tests | F51: 2 | G51: Pytest fixtures: hash embeddings, a temp Chroma folder, the shared sample docs, no LLM, and an ask() helper that posts to /invoke. | H51: settings, client (startup auto-ingests), auth fixtures; ask() | I51: used by test_api.py and test_pipeline.py; reads rag/data/sample-docs | J51: Tests run in seconds with no download or API key and never touch the real index. | K51: No
A52: 51 | B52: Librarian | C52: agents/python/knowledge-rag/tests | D52: test_api.py | E52: Tests | F52: 2 | G52: End-to-end API tests: auth, grounded answer with citations, not-found instead of guessing, ignored extra fields, doc_type filter, input validation, raw search, quarantine, re-ingest, and Claude citation validation with a fake client. | H52: test_grounded_answer_with_citations; test_not_found_instead_of_guessing; test_documents_and_quarantine; test_claude_citations_are_validated; test_refuses_weak_token | I52: exercises api/app.py and llm/answerer.py | J52: The fake-Claude test proves a hallucinated [9] citation is stripped. | K52: No
A53: 52 | B53: Librarian | C53: agents/python/knowledge-rag/tests | D53: test_pipeline.py | E53: Tests | F53: 2 | G53: Unit tests for each RAG step: front matter, chunking, safety quarantine, hash embedding similarity, idempotent ingest, removal of deleted docs, and retrieval correctness. | H53: test_chunks_follow_sections_and_keep_metadata; test_safety_quarantines_instructions; test_ingest_is_idempotent_and_quarantines; test_retriever_finds_right_document | I53: tests rag/ modules | J53: A retrieval test asserts an irrelevant question ('pizza in Chicago') returns nothing. | K53: No
A54: 53 | B54: Librarian | C54: agents/python/knowledge-rag | D54: .env.example | E54: Config | F54: 3 | G54: Template for environment variables for the Librarian: shared SERVICE_TOKEN, optional Anthropic key, embedding provider (minilm or hash) and RAG knobs. | H54: SERVICE_TOKEN; optional ANTHROPIC_API_KEY, LLM_MODEL (claude-haiku-4-5-20251001); port override | I54: copy values into aurelius/.env (shared) or an agent-level .env; read by src/core/config.py | J54: Secrets live in .env files, not code; the example file holds placeholders only. | K54: No
A55: 54 | B55: Librarian | C55: agents/python/knowledge-rag | D55: README.md | E55: Docs | F55: 3 | G55: Overview of the Librarian: purpose, port 8001, request flow, folder map and skills. | K55: No
A56: 55 | B56: Librarian | C56: agents/python/knowledge-rag | D56: TESTING.md | E56: Docs | F56: 3 | G56: Windows/PowerShell runbook for setting up the venv, starting the Librarian and running its tests. | I56: pytest in tests/; api-tests.http | K56: No
A57: 56 | B57: Librarian | C57: agents/python/knowledge-rag | D57: api-tests.http | E57: Tests | F57: 3 | G57: VS Code REST Client collection of manual HTTP requests against the Librarian on port 8001, with expected results noted in comments. | H57: requests for /health, agent card, /invoke skills, error cases | I57: used by hand against the running service; needs SERVICE_TOKEN pasted in | K57: No
A58: 57 | B58: Librarian | C58: agents/python/knowledge-rag | D58: pytest.ini | E58: Config | F58: 3 | G58: Pytest config: puts src on the import path and sets tests as the test folder. | H58: pythonpath = src; testpaths = tests | I58: read by pytest; same file in every Python agent | K58: No
A59: 58 | B59: Librarian | C59: agents/python/knowledge-rag | D59: requirements.txt | E59: Build / tooling | F59: 3 | G59: Lists packages for the Librarian: FastAPI stack, anthropic SDK, and chromadb (embedded vector DB with MiniLM embeddings). | H59: fastapi, uvicorn, pydantic, pydantic-settings, pytest, httpx plus agent-specific libs | I59: installed with pip into the agent's .venv | K59: No
A60: 59 | B60: Librarian | C60: agents/python/knowledge-rag/src/api | D60: __init__.py | E60: Build / tooling | F60: 3 | G60: Empty file that makes api a Python package. | K60: No
A61: 60 | B61: Librarian | C61: agents/python/knowledge-rag/src/core | D61: __init__.py | E61: Build / tooling | F61: 3 | G61: Empty file that makes core a Python package. | K61: No
A62: 61 | B62: Librarian | C62: agents/python/knowledge-rag/src/core | D62: log_setup.py | E62: Config | F62: 3 | G62: Sets up structured JSON logging to stdout, one object per line, so logs can be searched by trace id. | H62: JsonFormatter (ts, level, logger, msg, exc); setup_logging() replaces root handlers, level INFO; quiets httpx logger | I62: called by src/main.py build_app(); identical file in every Python agent | J62: Logs record ids, counts and timings only, never secrets or PII, and one JSON line per event is easy to search in Splunk or Datadog. | K62: No
A63: 62 | B63: Librarian | C63: agents/python/knowledge-rag/src/llm | D63: __init__.py | E63: Build / tooling | F63: 3 | G63: Empty file that makes llm a Python package. | K63: No
A64: 63 | B64: Librarian | C64: agents/python/knowledge-rag/src/rag | D64: __init__.py | E64: Build / tooling | F64: 3 | G64: Empty file that makes rag a Python package. | K64: No
A65: 64 | B65: Librarian | C65: agents/python/knowledge-rag/src/schemas | D65: __init__.py | E65: Build / tooling | F65: 3 | G65: Empty file that makes schemas a Python package. | K65: No
A66: 65 | B66: Librarian | C66: agents/python/knowledge-rag/src/security | D66: __init__.py | E66: Build / tooling | F66: 3 | G66: Empty file that makes security a Python package. | K66: No
A67: 66 | B67: Analyst | C67: agents/python/portfolio-insights/src/analysis | D67: engine.py | E67: Business logic | F67: 1 | G67: analyze_portfolio pipeline: code calls MCP tools in a fixed order, runs allocation, concentration and tax-loss checks, builds actions, then asks the narrator for a summary. | H67: analyze(): get_client_profile, get_holdings, get_recent_trades, get_security_info for harvestable lots; builds facts dict and AnalysisResult | I67: uses analysis/allocation.py, concentration.py, tax_loss.py, llm/narrator.py, mcp_client/client.py; called by api/app.py | J67: Code, not the LLM, decides which tools to run, which is predictable, cheap and auditable for a standard report. | K67: No
A68: 67 | B68: Analyst | C68: agents/python/portfolio-insights/src/api | D68: app.py | E68: API / routes | F68: 1 | G68: Builds the Analyst FastAPI app. /invoke runs analyze_portfolio or ask_portfolio against live data from MCP tools and maps MCP or LLM failures to error envelopes. | H68: GET /health (reports MCP up/down and tool count); GET /.well-known/agent.json; POST /invoke; GET /v1/tools (503 if MCP down); create_app(settings, mcp_target, llm_client) allows in-process injection | I68: calls analysis/engine.py, llm/tool_agent.py, llm/narrator.py, mcp_client/client.py, security/auth.py; called by the Conductor | J68: Dependency injection of the MCP target lets tests use an in-process fake server, and an MCP outage is reported as an error instead of a crash. | K68: No
A69: 68 | B69: Analyst | C69: agents/python/portfolio-insights/src/llm | D69: tool_agent.py | E69: Business logic | F69: 1 | G69: ask_portfolio: Claude runs an agent loop choosing MCP tools for a free-form question, with an allowlist, client scope pinning and a turn limit. | H69: ALLOWED_TOOLS (get_client_profile, get_holdings, get_recent_trades, get_security_info); ToolAgent.ask(); max_agent_turns 6; LLMUnavailable | I69: called by api/app.py; uses mcp_client/client.py PortfolioTools | J69: Scope pinning overwrites any client_id Claude supplies, so a prompt-injected request cannot read another household. | K69: No
A70: 69 | B70: Analyst | C70: agents/python/portfolio-insights/src | D70: main.py | E70: Entry point | F70: 1 | G70: Starts the Analyst with uvicorn on 127.0.0.1:8002; the advisor-tools MCP server on 8500 must be started first. | H70: build_app(); __main__ runs uvicorn with settings.port | I70: imports api/app.py, core/config.py, core/log_setup.py; depends on MCP server :8500 | K70: No
A71: 70 | B71: Analyst | C71: agents/python/portfolio-insights/src/mcp_client | D71: client.py | E71: Data access / clients | F71: 1 | G71: The only place that talks to the advisor-tools MCP server (streamable HTTP with a bearer token). Wraps connect, list_tools and call_tool and converts failures into clear exceptions. | H71: PortfolioTools async context manager; list_tools(); call() records each call; ToolCallError; MCPUnavailable; _root() unwraps ExceptionGroups; accepts an in-process server for tests | I71: calls MCP server :8500 /mcp; used by analysis/engine.py, llm/tool_agent.py, api/app.py | J71: The Analyst depends only on the MCP contract, so data could move to a real portfolio system without changing agent code. | K71: No
A72: 71 | B72: Analyst | C72: agents/python/portfolio-insights/src/schemas | D72: models.py | E72: Models / schemas | F72: 1 | G72: Pydantic models: shared agent contract, skill inputs and the outputs of analyze_portfolio and ask_portfolio. | H72: AnalyzeInput; AskInput (question 3-1000 chars); AllocationCheck; ConcentrationFlag; TaxLossIdea; AnalysisResult; AskResult | I72: used by api/app.py, analysis/*, llm/* | K72: No
A73: 72 | B73: Analyst | C73: agents/python/portfolio-insights/src/analysis | D73: allocation.py | E73: Business logic | F73: 2 | G73: Check 1: compares current asset-class percentages to the target and flags classes more than 5 points off (rebalancing policy). | H73: check_allocation(); ASSET_CLASSES equity, fixed_income, cash; drift = current - target; flag if abs(drift) > threshold | I73: called by analysis/engine.py; tested in tests/test_analysis.py | J73: All numbers are computed in code because LLMs are unreliable at arithmetic. | K73: No
A74: 73 | B74: Analyst | C74: agents/python/portfolio-insights/src/analysis | D74: concentration.py | E74: Business logic | F74: 2 | G74: Check 2: flags single stocks above 10 percent (review) or 15 percent (escalate) of household assets, summing the same stock across accounts and ignoring funds. | H74: check_concentration(); filters security_type == 'stock' | I74: called by analysis/engine.py; tested in tests/test_analysis.py | J74: Getting the rule's scope right (stocks, not diversified funds) matters as much as the arithmetic. | K74: No
A75: 74 | B75: Analyst | C75: agents/python/portfolio-insights/src/analysis | D75: tax_loss.py | E75: Business logic | F75: 2 | G75: Check 3: finds tax-loss harvesting ideas in taxable accounts with losses of at least $1,000 and flags wash-sale risk if the security was bought in any household account within 30 days. | H75: find_tax_loss_ideas(); recent_buys by symbol; note text says WAIT or suggests replacements | I75: called by analysis/engine.py; tested in tests/test_analysis.py | J75: The wash-sale check looks across all accounts including IRAs, which is the easy-to-miss part of the rule. | K75: No
A76: 75 | B76: Analyst | C76: agents/python/portfolio-insights/src/core | D76: config.py | E76: Config | F76: 2 | G76: Pydantic Settings for the Analyst: port, token, MCP URL and timeout, LLM settings, agent turn cap and the policy thresholds. | H76: Settings: port 8002 (ANALYST_PORT); mcp_advisor_tools_url http://127.0.0.1:8500/mcp; max_agent_turns 6; drift_threshold_pts 5; concentration 10/15; tlh_min_loss_usd 1000; wash_sale_days 30 | I76: used by all modules | J76: Thresholds mirror the policy documents the Librarian indexes; in production they would come from one rules service. | K76: No
A77: 76 | B77: Analyst | C77: agents/python/portfolio-insights/src/llm | D77: narrator.py | E77: Business logic | F77: 2 | G77: Turns pre-computed facts into a 3-5 sentence summary. Claude only writes prose from the facts JSON; without a key or on failure a deterministic template writes it. | H77: SYSTEM prompt (use only numbers in facts); template_summary(); Narrator.summarize() returns (text, answered_by) | I77: called by analysis/engine.py via api/app.py | J77: The LLM explains numbers but never computes them, and a template fallback keeps the skill working without a key. | K77: No
A78: 77 | B78: Analyst | C78: agents/python/portfolio-insights/src/security | D78: auth.py | E78: Security | F78: 2 | G78: Service-token authentication and a startup check that refuses a weak SERVICE_TOKEN. The same token is also sent to the MCP server. | H78: require_service(); check_startup_security() | I78: used by api/app.py | J78: Same fail-closed pattern as the other agents. | K78: No
A79: 78 | B79: Analyst | C79: agents/python/portfolio-insights/tests | D79: conftest.py | E79: Tests | F79: 2 | G79: Builds an in-process fake MCP server with the same tools and result shapes as advisor-tools, plus two sample households (busy-01, calm-02) and fixtures. | H79: build_fake_mcp(); SECURITIES; CLIENTS; pos(); settings, client, auth fixtures; invoke() | I79: used by test_api.py and test_analysis.py | J79: The fake server proves the Analyst depends only on the MCP contract, not on how data is stored. | K79: No
A80: 79 | B80: Analyst | C80: agents/python/portfolio-insights/tests | D80: test_analysis.py | E80: Tests | F80: 2 | G80: Unit tests of the three pure checks: drift, concentration levels and scope, tax-loss rules and wash-sale detection across accounts. | H80: test_drift_and_flags; test_concentration_only_counts_stocks; test_wash_sale_detected_across_accounts | I80: tests analysis/allocation.py, concentration.py, tax_loss.py | J80: Boundary cases (exactly 5.0 points is not over threshold) are tested explicitly. | K80: No
A81: 80 | B81: Analyst | C81: agents/python/portfolio-insights/tests | D81: test_api.py | E81: Tests | F81: 2 | G81: End-to-end tests from HTTP to the fake MCP server: health, analysis of both households, error envelopes, MCP down handling, and the Claude tool loop with scope pinning. | H81: test_analyze_busy_household; test_mcp_down_is_reported_not_crashed; test_tool_loop_with_scope_pinning; test_refuses_weak_token | I81: exercises api/app.py, mcp_client/client.py, llm/tool_agent.py | J81: The scope pinning test has a scripted Claude request another client's data and asserts the call was rewritten to the right client. | K81: No
A82: 81 | B82: Analyst | C82: agents/python/portfolio-insights | D82: .env.example | E82: Config | F82: 3 | G82: Template for environment variables for the Analyst: shared SERVICE_TOKEN, MCP server URL (127.0.0.1:8500), optional Anthropic key, and policy thresholds. | H82: SERVICE_TOKEN; optional ANTHROPIC_API_KEY, LLM_MODEL (claude-haiku-4-5-20251001); port override | I82: copy values into aurelius/.env (shared) or an agent-level .env; read by src/core/config.py | J82: Secrets live in .env files, not code; the example file holds placeholders only. | K82: No
A83: 82 | B83: Analyst | C83: agents/python/portfolio-insights | D83: README.md | E83: Docs | F83: 3 | G83: Overview of the Analyst: purpose, port 8002, request flow, folder map and skills. | K83: No
A84: 83 | B84: Analyst | C84: agents/python/portfolio-insights | D84: TESTING.md | E84: Docs | F84: 3 | G84: Windows/PowerShell runbook for setting up the venv, starting the Analyst and running its tests. | I84: pytest in tests/; api-tests.http | K84: No
A85: 84 | B85: Analyst | C85: agents/python/portfolio-insights | D85: api-tests.http | E85: Tests | F85: 3 | G85: VS Code REST Client collection of manual HTTP requests against the Analyst on port 8002, with expected results noted in comments. | H85: requests for /health, agent card, /invoke skills, error cases | I85: used by hand against the running service; needs SERVICE_TOKEN pasted in | K85: No
A86: 85 | B86: Analyst | C86: agents/python/portfolio-insights | D86: pytest.ini | E86: Config | F86: 3 | G86: Pytest config: puts src on the import path and sets tests as the test folder. | H86: pythonpath = src; testpaths = tests | I86: read by pytest; same file in every Python agent | K86: No
A87: 86 | B87: Analyst | C87: agents/python/portfolio-insights | D87: requirements.txt | E87: Build / tooling | F87: 3 | G87: Lists packages for the Analyst: FastAPI stack, anthropic SDK and the mcp client library (>=2.3,<3). | H87: fastapi, uvicorn, pydantic, pydantic-settings, pytest, httpx plus agent-specific libs | I87: installed with pip into the agent's .venv | K87: No
A88: 87 | B88: Analyst | C88: agents/python/portfolio-insights/src/analysis | D88: __init__.py | E88: Build / tooling | F88: 3 | G88: Empty file that makes analysis a Python package. | K88: No
A89: 88 | B89: Analyst | C89: agents/python/portfolio-insights/src/api | D89: __init__.py | E89: Build / tooling | F89: 3 | G89: Empty file that makes api a Python package. | K89: No
A90: 89 | B90: Analyst | C90: agents/python/portfolio-insights/src/core | D90: __init__.py | E90: Build / tooling | F90: 3 | G90: Empty file that makes core a Python package. | K90: No
A91: 90 | B91: Analyst | C91: agents/python/portfolio-insights/src/core | D91: log_setup.py | E91: Config | F91: 3 | G91: Sets up structured JSON logging to stdout, one object per line, so logs can be searched by trace id. | H91: JsonFormatter (ts, level, logger, msg, exc); setup_logging() replaces root handlers, level INFO; quiets httpx logger | I91: called by src/main.py build_app(); identical file in every Python agent | J91: Logs record ids, counts and timings only, never secrets or PII, and one JSON line per event is easy to search in Splunk or Datadog. | K91: No
A92: 91 | B92: Analyst | C92: agents/python/portfolio-insights/src/llm | D92: __init__.py | E92: Build / tooling | F92: 3 | G92: Empty file that makes llm a Python package. | K92: No
A93: 92 | B93: Analyst | C93: agents/python/portfolio-insights/src/mcp_client | D93: __init__.py | E93: Build / tooling | F93: 3 | G93: Empty file that makes mcp_client a Python package. | K93: No
A94: 93 | B94: Analyst | C94: agents/python/portfolio-insights/src/schemas | D94: __init__.py | E94: Build / tooling | F94: 3 | G94: Empty file that makes schemas a Python package. | K94: No
A95: 94 | B95: Analyst | C95: agents/python/portfolio-insights/src/security | D95: __init__.py | E95: Build / tooling | F95: 3 | G95: Empty file that makes security a Python package. | K95: No
A96: 95 | B96: Scribe | C96: agents/python/meeting-intel/src/api | D96: app.py | E96: API / routes | F96: 1 | G96: Builds the Scribe FastAPI app. /invoke routes two skills, summarize_meetings and extract_meeting; also lists stored meetings for a client. | H96: GET /health; GET /.well-known/agent.json; POST /invoke; GET /v1/meetings/{client_id}; client_id falls back to context.client_id; notes cap 20000 chars | I96: calls extract/service.py Scribe, notes/store.py, security/auth.py; called by the Conductor | J96: Extra input keys from the Conductor are filtered to the model's fields, and client_id is regex-validated to stop path tricks. | K96: No
A97: 96 | B97: Scribe | C97: agents/python/meeting-intel/src/extract | D97: llm.py | E97: Business logic | F97: 1 | G97: Claude structured extraction: MeetingExtract schema becomes a forced tool call (record_meeting) and the result is validated with pydantic before use; failures return None. | H97: SYSTEM prompt; _inline_refs(); TOOL; ClaudeExtractor.extract(); notes in <notes> tags; max_tokens 1500 | I97: called by extract/service.py; uses schemas/models.py MeetingExtract | J97: LLM output is never trusted: invalid structure is rejected and the caller falls back to rules. | K97: No
A98: 97 | B98: Scribe | C98: agents/python/meeting-intel/src/extract | D98: service.py | E98: Business logic | F98: 1 | G98: Core Scribe pipeline: mask PII, extract with Claude (validated) or fall back to rules, add a pii_in_notes flag in code, cache by hash, and combine several meetings into one summary. | H98: Scribe.extract_one(); Scribe.summarize(); sha256 cache key; asyncio.gather over meetings; dedupes action items, concerns, life events | I98: uses extract/redact.py, llm.py, rules.py, notes/store.py; called by api/app.py | J98: The PII flag is added by code so it never depends on the model noticing, and the cache avoids paying twice for the same notes. | K98: No
A99: 98 | B99: Scribe | C99: agents/python/meeting-intel/src | D99: main.py | E99: Entry point | F99: 1 | G99: Starts the Scribe with uvicorn on 127.0.0.1:8003 via an app factory with auto-reload. | H99: build_app(); __main__ runs uvicorn with settings.port | I99: imports api/app.py, core/config.py, core/log_setup.py | K99: No
A100: 99 | B100: Scribe | C100: agents/python/meeting-intel/src/schemas | D100: models.py | E100: Models / schemas | F100: 1 | G100: Pydantic models: shared agent contract, the MeetingExtract schema (used for the Claude tool schema, validation and rules output) and skill inputs and results. | H100: ActionItem; ComplianceFlag; MeetingExtract; SummarizeInput; ExtractInput; MeetingResult; SummarizeResult; client_id pattern ^[A-Za-z0-9_-]{1,64}$ | I100: used by api/app.py, extract/* | J100: One schema serves the LLM path, validation and the rules path, so both return the same shape. | K100: No
...
